Metadata-Version: 2.1
Name: elvisgogo
Version: 0.1.6
Summary: 数据挖掘实验4
Home-page: UNKNOWN
Author: lry
Author-email: 1224137702@qq.com
License: UNKNOWN
Platform: UNKNOWN
